{
  "id": "1582",
  "owner": "0x577ebc5de943e35cdf9ecb5bbe1f7d7cb6c7c647",
  "attributes": [
    "Female",
    "Messy Hair",
    "VR"
  ],
  "transactions": [
    {
      "Type": "Bid Withdrawn",
      "From": "0xd8cb8f",
      "To": "",
      "Amount": "24\u039e ($42,858)",
      "Date": "Mar 21, 2021"
    },
    {
      "Type": "Bid",
      "From": "0xd8cb8f",
      "To": "",
      "Amount": "24\u039e ($42,640)",
      "Date": "Mar 21, 2021"
    },
    {
      "Type": "Transfer",
      "From": "0xcbd482",
      "To": "0x577ebc",
      "Amount": "",
      "Date": "Jan 30, 2021"
    },
    {
      "Type": "Bid Withdrawn",
      "From": "0x4c9692",
      "To": "",
      "Amount": "1.23\u039e ($1,501)",
      "Date": "Jan 17, 2021"
    },
    {
      "Type": "Bid",
      "From": "0x4c9692",
      "To": "",
      "Amount": "1.23\u039e ($1,479)",
      "Date": "Jan 17, 2021"
    },
    {
      "Type": "Claimed",
      "From": "",
      "To": "0xcbd482",
      "Amount": "",
      "Date": "Jun 23, 2017"
    }
  ]
}