{
  "id": "2398",
  "owner": "0xb7f7f6c52f2e2fdb1963eab30438024864c313f6",
  "attributes": [
    "Female",
    "Mole",
    "Blue Eye Shadow",
    "Mohawk",
    "Cigarette"
  ],
  "transactions": [
    {
      "Type": "(Wrap)",
      "From": "0xbea00d",
      "To": "WrappedC\u2026",
      "Amount": "",
      "Date": "May 03, 2021"
    },
    {
      "Type": "Transfer",
      "From": "sexpunks\u2026",
      "To": "0xbea00d",
      "Amount": "",
      "Date": "May 03, 2021"
    },
    {
      "Type": "(Unwrap)",
      "From": "WrappedC\u2026",
      "To": "sexpunks\u2026",
      "Amount": "",
      "Date": "May 03, 2021"
    },
    {
      "Type": "(Wrap)",
      "From": "0xcb7624",
      "To": "WrappedC\u2026",
      "Amount": "",
      "Date": "May 03, 2021"
    },
    {
      "Type": "Transfer",
      "From": "0xc08be1",
      "To": "0xcb7624",
      "Amount": "",
      "Date": "May 03, 2021"
    },
    {
      "Type": "(Unwrap)",
      "From": "WrappedC\u2026",
      "To": "0xc08be1",
      "Amount": "",
      "Date": "May 03, 2021"
    },
    {
      "Type": "(Wrap)",
      "From": "0x051561",
      "To": "WrappedC\u2026",
      "Amount": "",
      "Date": "Feb 28, 2021"
    },
    {
      "Type": "Transfer",
      "From": "0xaae8c5",
      "To": "0x051561",
      "Amount": "",
      "Date": "Feb 28, 2021"
    },
    {
      "Type": "Offered",
      "From": "",
      "To": "",
      "Amount": "24.49\u039e ($34,668)",
      "Date": "Feb 28, 2021"
    },
    {
      "Type": "Bid Withdrawn",
      "From": "0x097761",
      "To": "",
      "Amount": "21\u039e ($29,243)",
      "Date": "Feb 28, 2021"
    },
    {
      "Type": "Bid",
      "From": "0x097761",
      "To": "",
      "Amount": "21\u039e ($29,243)",
      "Date": "Feb 28, 2021"
    },
    {
      "Type": "Offered",
      "From": "",
      "To": "",
      "Amount": "24.90\u039e ($33,880)",
      "Date": "Feb 28, 2021"
    },
    {
      "Type": "(Unwrap)",
      "From": "WrappedC\u2026",
      "To": "0xaae8c5",
      "Amount": "",
      "Date": "Feb 28, 2021"
    },
    {
      "Type": "(Wrap)",
      "From": "0xb1ad60",
      "To": "WrappedC\u2026",
      "Amount": "",
      "Date": "Dec 22, 2020"
    },
    {
      "Type": "Transfer",
      "From": "0x_NFT",
      "To": "0xb1ad60",
      "Amount": "",
      "Date": "Dec 22, 2020"
    },
    {
      "Type": "Sold",
      "From": "Pixls",
      "To": "0x_NFT",
      "Amount": "4.50\u039e ($1,551)",
      "Date": "Sep 25, 2020"
    },
    {
      "Type": "Offered",
      "From": "",
      "To": "",
      "Amount": "4.50\u039e ($1,658)",
      "Date": "Sep 15, 2020"
    },
    {
      "Type": "Offered",
      "From": "",
      "To": "",
      "Amount": "10\u039e ($3,700)",
      "Date": "Sep 15, 2020"
    },
    {
      "Type": "Offered",
      "From": "",
      "To": "",
      "Amount": "3\u039e ($600)",
      "Date": "May 26, 2020"
    },
    {
      "Type": "Offered",
      "From": "",
      "To": "",
      "Amount": "2\u039e ($327)",
      "Date": "Jan 16, 2020"
    },
    {
      "Type": "Offered",
      "From": "",
      "To": "",
      "Amount": "1.10\u039e ($153)",
      "Date": "Jan 09, 2020"
    },
    {
      "Type": "Offered",
      "From": "",
      "To": "",
      "Amount": "0.96\u039e ($126)",
      "Date": "Dec 31, 2019"
    },
    {
      "Type": "Offered",
      "From": "",
      "To": "",
      "Amount": "1.40\u039e ($265)",
      "Date": "Sep 15, 2019"
    },
    {
      "Type": "Offered",
      "From": "",
      "To": "",
      "Amount": "0.77\u039e ($127)",
      "Date": "Apr 13, 2019"
    },
    {
      "Type": "Offered",
      "From": "",
      "To": "",
      "Amount": "0.90\u039e ($107)",
      "Date": "Jan 20, 2019"
    },
    {
      "Type": "Offered",
      "From": "",
      "To": "",
      "Amount": "0.37\u039e ($56)",
      "Date": "Jan 07, 2019"
    },
    {
      "Type": "Sold",
      "From": "Cyborg",
      "To": "Pixls",
      "Amount": "0.28\u039e ($42)",
      "Date": "Jan 07, 2019"
    },
    {
      "Type": "Offered",
      "From": "",
      "To": "",
      "Amount": "0.28\u039e ($42)",
      "Date": "Jan 07, 2019"
    },
    {
      "Type": "Offered",
      "From": "",
      "To": "",
      "Amount": "1\u039e ($486)",
      "Date": "Mar 26, 2018"
    },
    {
      "Type": "Sold",
      "From": "0xd8e806",
      "To": "Cyborg",
      "Amount": "0.18\u039e ($55)",
      "Date": "Aug 12, 2017"
    },
    {
      "Type": "Offered",
      "From": "",
      "To": "",
      "Amount": "0.18\u039e ($55)",
      "Date": "Aug 12, 2017"
    },
    {
      "Type": "Offered",
      "From": "",
      "To": "",
      "Amount": "0.20\u039e ($62)",
      "Date": "Aug 12, 2017"
    },
    {
      "Type": "Offer Withdrawn",
      "From": "",
      "To": "",
      "Amount": "",
      "Date": "Jul 13, 2017"
    },
    {
      "Type": "Offered",
      "From": "",
      "To": "",
      "Amount": "0.75\u039e ($143)",
      "Date": "Jul 11, 2017"
    },
    {
      "Type": "Sold",
      "From": "0x22160e",
      "To": "0xd8e806",
      "Amount": "0.39\u039e ($74)",
      "Date": "Jul 11, 2017"
    },
    {
      "Type": "Offered",
      "From": "",
      "To": "",
      "Amount": "0.39\u039e ($74)",
      "Date": "Jul 11, 2017"
    },
    {
      "Type": "Offered",
      "From": "",
      "To": "",
      "Amount": "0.44\u039e ($84)",
      "Date": "Jul 11, 2017"
    },
    {
      "Type": "Claimed",
      "From": "",
      "To": "0x22160e",
      "Amount": "",
      "Date": "Jun 23, 2017"
    }
  ]
}