{
  "id": "3037",
  "owner": "0x8ca89c56aefd379baa15e0ec91c7f5ae7f5b096f",
  "attributes": [
    "Female",
    "Hot Lipstick",
    "Blonde Bob"
  ],
  "transactions": [
    {
      "Type": "Sold",
      "From": "Hemba",
      "To": "0x8ca89c",
      "Amount": "0.12\u039e ($83)",
      "Date": "Dec 14, 2017"
    },
    {
      "Type": "Offered",
      "From": "",
      "To": "",
      "Amount": "0.12\u039e ($84)",
      "Date": "Dec 13, 2017"
    },
    {
      "Type": "Transfer",
      "From": "0xe4d36b",
      "To": "Hemba",
      "Amount": "",
      "Date": "Jun 28, 2017"
    },
    {
      "Type": "Claimed",
      "From": "",
      "To": "0xe4d36b",
      "Amount": "",
      "Date": "Jun 23, 2017"
    }
  ]
}