{
  "id": "3049",
  "owner": "0xe9e7b800ec5fc6015cf6b2826711254bab3c12e4",
  "attributes": [
    "Male",
    "Hoodie",
    "Goat"
  ],
  "transactions": [
    {
      "Type": "Sold",
      "From": "Deeze",
      "To": "0xe9e7b8",
      "Amount": "7.19\u039e ($3,429)",
      "Date": "Nov 19, 2020"
    },
    {
      "Type": "Offered",
      "From": "",
      "To": "",
      "Amount": "7.19\u039e ($3,315)",
      "Date": "Nov 14, 2020"
    },
    {
      "Type": "Offered",
      "From": "",
      "To": "",
      "Amount": "7.69\u039e ($2,981)",
      "Date": "Nov 02, 2020"
    },
    {
      "Type": "Offered",
      "From": "",
      "To": "",
      "Amount": "9.69\u039e ($3,797)",
      "Date": "Oct 29, 2020"
    },
    {
      "Type": "Offered",
      "From": "",
      "To": "",
      "Amount": "12.77\u039e ($4,860)",
      "Date": "Oct 13, 2020"
    },
    {
      "Type": "Offered",
      "From": "",
      "To": "",
      "Amount": "14.69\u039e ($5,509)",
      "Date": "Oct 10, 2020"
    },
    {
      "Type": "Offered",
      "From": "",
      "To": "",
      "Amount": "19.97\u039e ($6,816)",
      "Date": "Oct 07, 2020"
    },
    {
      "Type": "Sold",
      "From": "0xa3cb30",
      "To": "Deeze",
      "Amount": "7\u039e ($2,387)",
      "Date": "Oct 07, 2020"
    },
    {
      "Type": "Bid Withdrawn",
      "From": "Deeze",
      "To": "",
      "Amount": "6.66\u039e ($2,271)",
      "Date": "Oct 07, 2020"
    },
    {
      "Type": "Offered",
      "From": "",
      "To": "",
      "Amount": "7\u039e ($2,387)",
      "Date": "Oct 07, 2020"
    },
    {
      "Type": "Bid",
      "From": "Deeze",
      "To": "",
      "Amount": "6.66\u039e ($2,273)",
      "Date": "Oct 07, 2020"
    },
    {
      "Type": "Bid Withdrawn",
      "From": "Alex3422",
      "To": "",
      "Amount": "5\u039e ($1,756)",
      "Date": "Oct 06, 2020"
    },
    {
      "Type": "Bid",
      "From": "Alex3422",
      "To": "",
      "Amount": "5\u039e ($1,765)",
      "Date": "Oct 06, 2020"
    },
    {
      "Type": "Transfer",
      "From": "0x00bd9f",
      "To": "0xa3cb30",
      "Amount": "",
      "Date": "Mar 07, 2018"
    },
    {
      "Type": "Claimed",
      "From": "",
      "To": "0x00bd9f",
      "Amount": "",
      "Date": "Jun 23, 2017"
    }
  ]
}