{
  "id": "33",
  "owner": "0x6611fe71c233e4e7510b2795c242c9a57790b376",
  "attributes": [
    "Male",
    "Peak Spike"
  ],
  "transactions": [
    {
      "Type": "Bid Withdrawn",
      "From": "dafky200\u2026",
      "To": "",
      "Amount": "2\u039e ($813)",
      "Date": "Nov 04, 2020"
    },
    {
      "Type": "Bid",
      "From": "dafky200\u2026",
      "To": "",
      "Amount": "2\u039e ($770)",
      "Date": "Nov 02, 2020"
    },
    {
      "Type": "Sold",
      "From": "0xc352b5",
      "To": "0x6611fe",
      "Amount": "0.51\u039e ($105)",
      "Date": "Jul 10, 2017"
    },
    {
      "Type": "Bid",
      "From": "0x6611fe",
      "To": "",
      "Amount": "0.51\u039e ($123)",
      "Date": "Jul 07, 2017"
    },
    {
      "Type": "Claimed",
      "From": "",
      "To": "0xc352b5",
      "Amount": "",
      "Date": "Jun 23, 2017"
    }
  ]
}