{
  "id": "3395",
  "owner": "0xee8dbe16568254450d890c1cb98180a770e82724",
  "attributes": [
    "Male",
    "Clown Nose",
    "Cap",
    "Big Shades",
    "Mole"
  ],
  "transactions": [
    {
      "Type": "Sold",
      "From": "0xbe0c0d",
      "To": "0xee8dbe",
      "Amount": "38\u039e ($92,122)",
      "Date": "Apr 15, 2021"
    },
    {
      "Type": "Bid",
      "From": "0xee8dbe",
      "To": "",
      "Amount": "38\u039e ($88,969)",
      "Date": "Apr 14, 2021"
    },
    {
      "Type": "Offered",
      "From": "",
      "To": "",
      "Amount": "39.99\u039e ($85,608)",
      "Date": "Apr 12, 2021"
    },
    {
      "Type": "Offered",
      "From": "",
      "To": "",
      "Amount": "40.99\u039e ($87,566)",
      "Date": "Apr 11, 2021"
    },
    {
      "Type": "Offered",
      "From": "",
      "To": "",
      "Amount": "41.99\u039e ($89,588)",
      "Date": "Apr 10, 2021"
    },
    {
      "Type": "Offered",
      "From": "",
      "To": "",
      "Amount": "44.99\u039e ($95,086)",
      "Date": "Apr 05, 2021"
    },
    {
      "Type": "Offered",
      "From": "",
      "To": "",
      "Amount": "34\u039e ($70,689)",
      "Date": "Apr 05, 2021"
    },
    {
      "Type": "Offered",
      "From": "",
      "To": "",
      "Amount": "35.50\u039e ($73,357)",
      "Date": "Apr 04, 2021"
    },
    {
      "Type": "Offered",
      "From": "",
      "To": "",
      "Amount": "37.50\u039e ($77,647)",
      "Date": "Apr 03, 2021"
    },
    {
      "Type": "Offered",
      "From": "",
      "To": "",
      "Amount": "39\u039e ($65,914)",
      "Date": "Mar 28, 2021"
    },
    {
      "Type": "Offered",
      "From": "",
      "To": "",
      "Amount": "42\u039e ($70,887)",
      "Date": "Mar 27, 2021"
    },
    {
      "Type": "Offered",
      "From": "",
      "To": "",
      "Amount": "44\u039e ($73,600)",
      "Date": "Mar 23, 2021"
    },
    {
      "Type": "Offered",
      "From": "",
      "To": "",
      "Amount": "48\u039e ($81,212)",
      "Date": "Mar 23, 2021"
    },
    {
      "Type": "Bid Withdrawn",
      "From": "0xddfdcb",
      "To": "",
      "Amount": "25\u039e ($44,973)",
      "Date": "Mar 21, 2021"
    },
    {
      "Type": "Sold",
      "From": "0x6f1724",
      "To": "0xbe0c0d",
      "Amount": "40\u039e ($71,956)",
      "Date": "Mar 21, 2021"
    },
    {
      "Type": "Bid",
      "From": "0xddfdcb",
      "To": "",
      "Amount": "25\u039e ($44,973)",
      "Date": "Mar 21, 2021"
    },
    {
      "Type": "Offered",
      "From": "",
      "To": "",
      "Amount": "40\u039e ($71,956)",
      "Date": "Mar 21, 2021"
    },
    {
      "Type": "Offered",
      "From": "",
      "To": "",
      "Amount": "50\u039e ($89,945)",
      "Date": "Mar 21, 2021"
    },
    {
      "Type": "Bid Withdrawn",
      "From": "0x36d1b7",
      "To": "",
      "Amount": "24\u039e ($42,424)",
      "Date": "Mar 21, 2021"
    },
    {
      "Type": "Bid",
      "From": "0x36d1b7",
      "To": "",
      "Amount": "24\u039e ($42,448)",
      "Date": "Mar 21, 2021"
    },
    {
      "Type": "Offered",
      "From": "",
      "To": "",
      "Amount": "100\u039e ($176,865)",
      "Date": "Mar 21, 2021"
    },
    {
      "Type": "Bid Withdrawn",
      "From": "0x36d1b7",
      "To": "",
      "Amount": "21.25\u039e ($37,584)",
      "Date": "Mar 21, 2021"
    },
    {
      "Type": "Bid",
      "From": "0x36d1b7",
      "To": "",
      "Amount": "21.25\u039e ($37,584)",
      "Date": "Mar 21, 2021"
    },
    {
      "Type": "Bid",
      "From": "0x62bdc6",
      "To": "",
      "Amount": "21.10\u039e ($37,319)",
      "Date": "Mar 21, 2021"
    },
    {
      "Type": "Bid",
      "From": "0x603a8f",
      "To": "",
      "Amount": "21\u039e ($37,142)",
      "Date": "Mar 21, 2021"
    },
    {
      "Type": "Bid",
      "From": "0x36d1b7",
      "To": "",
      "Amount": "20.20\u039e ($35,727)",
      "Date": "Mar 21, 2021"
    },
    {
      "Type": "Bid",
      "From": "0x62bdc6",
      "To": "",
      "Amount": "20.10\u039e ($35,550)",
      "Date": "Mar 21, 2021"
    },
    {
      "Type": "Bid",
      "From": "0x36d1b7",
      "To": "",
      "Amount": "20\u039e ($35,373)",
      "Date": "Mar 21, 2021"
    },
    {
      "Type": "Sold",
      "From": "0xde0193",
      "To": "0x6f1724",
      "Amount": "0.40\u039e ($49)",
      "Date": "Jan 16, 2019"
    },
    {
      "Type": "Bid Withdrawn",
      "From": "Dude_Nak\u2026",
      "To": "",
      "Amount": "0.20\u039e ($44)",
      "Date": "Nov 07, 2018"
    },
    {
      "Type": "Bid",
      "From": "Dude_Nak\u2026",
      "To": "",
      "Amount": "0.20\u039e ($41)",
      "Date": "Oct 28, 2018"
    },
    {
      "Type": "Offered",
      "From": "",
      "To": "",
      "Amount": "0.40\u039e ($274)",
      "Date": "Dec 15, 2017"
    },
    {
      "Type": "Claimed",
      "From": "",
      "To": "0xde0193",
      "Amount": "",
      "Date": "Jun 23, 2017"
    }
  ]
}