{
  "id": "3972",
  "owner": "0x04a30167ceea301c16c810a1a59f29e40cf895af",
  "attributes": [
    "Male",
    "Stringy Hair",
    "Chinstrap"
  ],
  "transactions": [
    {
      "Type": "Transfer",
      "From": "0xba681f",
      "To": "0x04a301",
      "Amount": "",
      "Date": "Feb 13, 2021"
    },
    {
      "Type": "Sold",
      "From": "0x6f4a2d",
      "To": "0xba681f",
      "Amount": "6.12\u039e ($11,368)",
      "Date": "Feb 13, 2021"
    },
    {
      "Type": "Offered",
      "From": "",
      "To": "",
      "Amount": "6.12\u039e ($10,918)",
      "Date": "Feb 11, 2021"
    },
    {
      "Type": "Claimed",
      "From": "",
      "To": "0x6f4a2d",
      "Amount": "",
      "Date": "Jun 23, 2017"
    }
  ]
}