{
  "id": "4296",
  "owner": "0x6f4a2d3a4f47f9c647d86c929755593911ee91ec",
  "attributes": [
    "Male",
    "Shadow Beard",
    "Do-rag",
    "Regular Shades",
    "Mole"
  ],
  "transactions": [
    {
      "Type": "Offer Withdrawn",
      "From": "",
      "To": "",
      "Amount": "",
      "Date": "Feb 20, 2021"
    },
    {
      "Type": "Offered",
      "From": "",
      "To": "",
      "Amount": "16\u039e ($29,199)",
      "Date": "Feb 14, 2021"
    },
    {
      "Type": "Claimed",
      "From": "",
      "To": "0x6f4a2d",
      "Amount": "",
      "Date": "Jun 23, 2017"
    }
  ]
}