{
  "id": "4466",
  "owner": "0x009988ff77eeaa00051238ee32c48f10a174933e",
  "attributes": [
    "Male",
    "Cigarette",
    "Do-rag"
  ],
  "transactions": [
    {
      "Type": "Transfer",
      "From": "0x270ff2",
      "To": "0x009988",
      "Amount": "",
      "Date": "May 09, 2021"
    },
    {
      "Type": "Transfer",
      "From": "0xb08be7",
      "To": "0x270ff2",
      "Amount": "",
      "Date": "May 07, 2021"
    },
    {
      "Type": "Transfer",
      "From": "0xa12474",
      "To": "0xb08be7",
      "Amount": "",
      "Date": "May 07, 2021"
    },
    {
      "Type": "Transfer",
      "From": "0xb08be7",
      "To": "0xa12474",
      "Amount": "",
      "Date": "May 06, 2021"
    },
    {
      "Type": "Transfer",
      "From": "0xe0ce99",
      "To": "0xb08be7",
      "Amount": "",
      "Date": "May 06, 2021"
    },
    {
      "Type": "Transfer",
      "From": "0xb08be7",
      "To": "0xe0ce99",
      "Amount": "",
      "Date": "May 06, 2021"
    },
    {
      "Type": "Sold",
      "From": "0xacaa0a",
      "To": "0xb08be7",
      "Amount": "25.88\u039e ($89,476)",
      "Date": "May 06, 2021"
    },
    {
      "Type": "Bid Withdrawn",
      "From": "wookie.e\u2026",
      "To": "",
      "Amount": "22\u039e ($74,704)",
      "Date": "May 04, 2021"
    },
    {
      "Type": "Bid",
      "From": "wookie.e\u2026",
      "To": "",
      "Amount": "22\u039e ($70,639)",
      "Date": "May 04, 2021"
    },
    {
      "Type": "Offered",
      "From": "",
      "To": "",
      "Amount": "25.88\u039e ($41,120)",
      "Date": "Feb 24, 2021"
    },
    {
      "Type": "Sold",
      "From": "0x6f4a2d",
      "To": "0xacaa0a",
      "Amount": "20\u039e ($38,371)",
      "Date": "Feb 22, 2021"
    },
    {
      "Type": "Offered",
      "From": "",
      "To": "",
      "Amount": "20\u039e ($38,371)",
      "Date": "Feb 22, 2021"
    },
    {
      "Type": "Claimed",
      "From": "",
      "To": "0x6f4a2d",
      "Amount": "",
      "Date": "Jun 23, 2017"
    }
  ]
}