{
  "id": "4684",
  "owner": "0xfaf20a6a1816e1490f46a67607c2889725638018",
  "attributes": [
    "Male",
    "Cigarette",
    "Shadow Beard",
    "Earring",
    "Do-rag"
  ],
  "transactions": [
    {
      "Type": "Sold",
      "From": "0xfab9b8",
      "To": "0xfaf20a",
      "Amount": "5.85\u039e ($9,567)",
      "Date": "Feb 04, 2021"
    },
    {
      "Type": "Offered",
      "From": "",
      "To": "",
      "Amount": "5.85\u039e ($9,544)",
      "Date": "Feb 03, 2021"
    },
    {
      "Type": "Transfer",
      "From": "0x2db1c4",
      "To": "0xfab9b8",
      "Amount": "",
      "Date": "Dec 28, 2019"
    },
    {
      "Type": "Sold",
      "From": "Hemba",
      "To": "0x2db1c4",
      "Amount": "0.14\u039e ($25)",
      "Date": "Nov 18, 2018"
    },
    {
      "Type": "Offered",
      "From": "",
      "To": "",
      "Amount": "0.14\u039e ($31)",
      "Date": "Nov 07, 2018"
    },
    {
      "Type": "Claimed",
      "From": "",
      "To": "Hemba",
      "Amount": "",
      "Date": "Jun 23, 2017"
    }
  ]
}