{
  "id": "5826",
  "owner": "0xecc1c49196f9be6c3028fae4dba2220839d28e8a",
  "attributes": [
    "Female",
    "Knitted Cap",
    "Purple Lipstick",
    "Clown Eyes Blue"
  ],
  "transactions": [
    {
      "Type": "Sold",
      "From": "0xa3cb30",
      "To": "0xecc1c4",
      "Amount": "13.99\u039e ($25,743)",
      "Date": "Feb 18, 2021"
    },
    {
      "Type": "Offered",
      "From": "",
      "To": "",
      "Amount": "13.99\u039e ($25,302)",
      "Date": "Feb 17, 2021"
    },
    {
      "Type": "Bid Withdrawn",
      "From": "0xbfa319",
      "To": "",
      "Amount": "0.42\u039e ($544)",
      "Date": "Jan 20, 2021"
    },
    {
      "Type": "Offered",
      "From": "",
      "To": "",
      "Amount": "11\u039e ($12,548)",
      "Date": "Jan 15, 2021"
    },
    {
      "Type": "Bid",
      "From": "0xbfa319",
      "To": "",
      "Amount": "0.42\u039e ($159)",
      "Date": "Oct 15, 2020"
    },
    {
      "Type": "Offered",
      "From": "",
      "To": "",
      "Amount": "6.85\u039e ($2,402)",
      "Date": "Oct 03, 2020"
    },
    {
      "Type": "Transfer",
      "From": "0x00bd9f",
      "To": "0xa3cb30",
      "Amount": "",
      "Date": "Mar 08, 2018"
    },
    {
      "Type": "Claimed",
      "From": "",
      "To": "0x00bd9f",
      "Amount": "",
      "Date": "Jun 23, 2017"
    }
  ]
}