{
  "id": "6598",
  "owner": "0x16c5d765eda967ef0e053023de583fd62554f2a3",
  "attributes": [
    "Female",
    "Big Shades",
    "Black Lipstick",
    "Straight Hair"
  ],
  "transactions": [
    {
      "Type": "Sold",
      "From": "0x65ba4f",
      "To": "0x16c5d7",
      "Amount": "33.30\u039e ($50,895)",
      "Date": "Feb 23, 2021"
    },
    {
      "Type": "Offered",
      "From": "",
      "To": "",
      "Amount": "33.30\u039e ($63,870)",
      "Date": "Feb 22, 2021"
    },
    {
      "Type": "Offered",
      "From": "",
      "To": "",
      "Amount": "29.40\u039e ($58,004)",
      "Date": "Feb 21, 2021"
    },
    {
      "Type": "Offered",
      "From": "",
      "To": "",
      "Amount": "26\u039e ($49,848)",
      "Date": "Feb 20, 2021"
    },
    {
      "Type": "Offered",
      "From": "",
      "To": "",
      "Amount": "29\u039e ($55,692)",
      "Date": "Feb 19, 2021"
    },
    {
      "Type": "Sold",
      "From": "MrTpunks",
      "To": "0x65ba4f",
      "Amount": "20\u039e ($37,784)",
      "Date": "Feb 18, 2021"
    },
    {
      "Type": "Offered",
      "From": "",
      "To": "",
      "Amount": "20\u039e ($37,784)",
      "Date": "Feb 18, 2021"
    },
    {
      "Type": "(Unwrap)",
      "From": "WrappedC\u2026",
      "To": "MrTpunks",
      "Amount": "",
      "Date": "Nov 07, 2020"
    },
    {
      "Type": "Sold",
      "From": "0x4fa27c",
      "To": "MrTpunks",
      "Amount": "8\u039e ($3,492)",
      "Date": "Nov 07, 2020"
    },
    {
      "Type": "(Wrap)",
      "From": "0x6a6936",
      "To": "WrappedC\u2026",
      "Amount": "",
      "Date": "Nov 07, 2020"
    },
    {
      "Type": "Transfer",
      "From": "0x4fa27c",
      "To": "0x6a6936",
      "Amount": "",
      "Date": "Nov 07, 2020"
    },
    {
      "Type": "Sold",
      "From": "NeonNFT",
      "To": "0x4fa27c",
      "Amount": "8\u039e ($2,932)",
      "Date": "Oct 16, 2020"
    },
    {
      "Type": "Bid Withdrawn",
      "From": "MrTpunks\u2026",
      "To": "",
      "Amount": "7\u039e ($2,585)",
      "Date": "Oct 16, 2020"
    },
    {
      "Type": "Bid",
      "From": "MrTpunks\u2026",
      "To": "",
      "Amount": "7\u039e ($2,589)",
      "Date": "Oct 16, 2020"
    },
    {
      "Type": "Offered",
      "From": "",
      "To": "",
      "Amount": "8\u039e ($2,955)",
      "Date": "Oct 16, 2020"
    },
    {
      "Type": "(Unwrap)",
      "From": "WrappedC\u2026",
      "To": "NeonNFT",
      "Amount": "",
      "Date": "Oct 07, 2020"
    },
    {
      "Type": "(Wrap)",
      "From": "0x0f8722",
      "To": "WrappedC\u2026",
      "Amount": "",
      "Date": "Oct 03, 2020"
    },
    {
      "Type": "Transfer",
      "From": "NeonNFT",
      "To": "0x0f8722",
      "Amount": "",
      "Date": "Oct 03, 2020"
    },
    {
      "Type": "Offered",
      "From": "",
      "To": "",
      "Amount": "12\u039e ($4,413)",
      "Date": "Oct 01, 2020"
    },
    {
      "Type": "Transfer",
      "From": "metakid",
      "To": "NeonNFT",
      "Amount": "",
      "Date": "Sep 28, 2020"
    },
    {
      "Type": "Claimed",
      "From": "",
      "To": "metakid",
      "Amount": "",
      "Date": "Jun 23, 2017"
    }
  ]
}