{
  "id": "6904",
  "owner": "0x289d953cf25d51abbc825faac3c260c10eda72cf",
  "attributes": [
    "Female",
    "Eye Mask",
    "Hot Lipstick",
    "Dark Hair"
  ],
  "transactions": [
    {
      "Type": "(Unwrap)",
      "From": "WrappedC\u2026",
      "To": "Zieg",
      "Amount": "",
      "Date": "Oct 07, 2020"
    },
    {
      "Type": "(Wrap)",
      "From": "0x33583f",
      "To": "WrappedC\u2026",
      "Amount": "",
      "Date": "Sep 29, 2020"
    },
    {
      "Type": "Transfer",
      "From": "Zieg",
      "To": "0x33583f",
      "Amount": "",
      "Date": "Sep 29, 2020"
    },
    {
      "Type": "Sold",
      "From": "Davicio",
      "To": "Zieg",
      "Amount": "3\u039e ($1,100)",
      "Date": "Sep 14, 2020"
    },
    {
      "Type": "Offered",
      "From": "",
      "To": "",
      "Amount": "3\u039e ($722)",
      "Date": "Jun 06, 2020"
    },
    {
      "Type": "Offer Withdrawn",
      "From": "",
      "To": "",
      "Amount": "",
      "Date": "Jun 06, 2020"
    },
    {
      "Type": "Bid Withdrawn",
      "From": "_K_A_M_I\u2026",
      "To": "",
      "Amount": "2.20\u039e ($454)",
      "Date": "May 28, 2020"
    },
    {
      "Type": "Offered",
      "From": "",
      "To": "",
      "Amount": "2.39\u039e ($493)",
      "Date": "May 28, 2020"
    },
    {
      "Type": "Bid",
      "From": "_K_A_M_I\u2026",
      "To": "",
      "Amount": "2.20\u039e ($454)",
      "Date": "May 28, 2020"
    },
    {
      "Type": "Sold",
      "From": "MadMax",
      "To": "Davicio",
      "Amount": "1.95\u039e ($400)",
      "Date": "May 28, 2020"
    },
    {
      "Type": "Offered",
      "From": "",
      "To": "",
      "Amount": "1.95\u039e ($403)",
      "Date": "May 27, 2020"
    },
    {
      "Type": "Sold",
      "From": "Pranksy",
      "To": "MadMax",
      "Amount": "1\u039e ($200)",
      "Date": "May 15, 2020"
    },
    {
      "Type": "Bid",
      "From": "MadMax",
      "To": "",
      "Amount": "1\u039e ($200)",
      "Date": "May 15, 2020"
    },
    {
      "Type": "Offered",
      "From": "",
      "To": "",
      "Amount": "1.19\u039e ($233)",
      "Date": "Apr 28, 2020"
    },
    {
      "Type": "Bid Withdrawn",
      "From": "jmg",
      "To": "",
      "Amount": "0.85\u039e ($142)",
      "Date": "Jan 21, 2020"
    },
    {
      "Type": "Bid",
      "From": "jmg",
      "To": "",
      "Amount": "0.85\u039e ($142)",
      "Date": "Jan 20, 2020"
    },
    {
      "Type": "Offered",
      "From": "",
      "To": "",
      "Amount": "1.49\u039e ($264)",
      "Date": "Jan 18, 2020"
    },
    {
      "Type": "Offered",
      "From": "",
      "To": "",
      "Amount": "0.99\u039e ($133)",
      "Date": "Jan 04, 2020"
    },
    {
      "Type": "Offered",
      "From": "",
      "To": "",
      "Amount": "0.65\u039e ($135)",
      "Date": "Sep 17, 2019"
    },
    {
      "Type": "Offered",
      "From": "",
      "To": "",
      "Amount": "0.72\u039e ($126)",
      "Date": "Sep 05, 2019"
    },
    {
      "Type": "Sold",
      "From": "0x00d7c9",
      "To": "Pranksy",
      "Amount": "0.25\u039e ($45)",
      "Date": "Sep 02, 2019"
    },
    {
      "Type": "Offered",
      "From": "",
      "To": "Pranksy",
      "Amount": "0.25\u039e ($45)",
      "Date": "Sep 02, 2019"
    },
    {
      "Type": "Offered",
      "From": "",
      "To": "",
      "Amount": "1\u039e ($269)",
      "Date": "Jul 13, 2019"
    },
    {
      "Type": "Claimed",
      "From": "",
      "To": "0x00d7c9",
      "Amount": "",
      "Date": "Jun 23, 2017"
    }
  ]
}