{
  "id": "7299",
  "owner": "0x9ae8912ea6562957043c8d048641aa9b450c397f",
  "attributes": [
    "Female",
    "Pipe",
    "Bandana",
    "Purple Lipstick"
  ],
  "transactions": [
    {
      "Type": "Sold",
      "From": "Michel_M\u2026",
      "To": "snax",
      "Amount": "3.05\u039e ($1,174)",
      "Date": "Sep 18, 2020"
    },
    {
      "Type": "Bid",
      "From": "snax",
      "To": "",
      "Amount": "3.05\u039e ($1,174)",
      "Date": "Sep 18, 2020"
    },
    {
      "Type": "Offer Withdrawn",
      "From": "",
      "To": "",
      "Amount": "",
      "Date": "Sep 16, 2020"
    },
    {
      "Type": "Offered",
      "From": "",
      "To": "",
      "Amount": "5.50\u039e ($1,996)",
      "Date": "Sep 16, 2020"
    },
    {
      "Type": "Offered",
      "From": "",
      "To": "",
      "Amount": "6.50\u039e ($2,377)",
      "Date": "Sep 15, 2020"
    },
    {
      "Type": "Offer Withdrawn",
      "From": "",
      "To": "",
      "Amount": "",
      "Date": "Jun 30, 2020"
    },
    {
      "Type": "Offered",
      "From": "",
      "To": "",
      "Amount": "2.75\u039e ($625)",
      "Date": "Jun 28, 2020"
    },
    {
      "Type": "Offer Withdrawn",
      "From": "",
      "To": "",
      "Amount": "",
      "Date": "Jun 18, 2020"
    },
    {
      "Type": "Offered",
      "From": "",
      "To": "",
      "Amount": "3.50\u039e ($826)",
      "Date": "Jun 14, 2020"
    },
    {
      "Type": "Offer Withdrawn",
      "From": "",
      "To": "",
      "Amount": "",
      "Date": "Jun 14, 2020"
    },
    {
      "Type": "Offered",
      "From": "",
      "To": "0x000000",
      "Amount": "0.00\u039e ($0.00)",
      "Date": "Jun 14, 2020"
    },
    {
      "Type": "Sold",
      "From": "Hemba",
      "To": "Michel_M\u2026",
      "Amount": "1.45\u039e ($344)",
      "Date": "Jun 13, 2020"
    },
    {
      "Type": "Bid Withdrawn",
      "From": "Michel_M\u2026",
      "To": "",
      "Amount": "1.35\u039e ($320)",
      "Date": "Jun 13, 2020"
    },
    {
      "Type": "Offered",
      "From": "",
      "To": "",
      "Amount": "1.45\u039e ($344)",
      "Date": "Jun 13, 2020"
    },
    {
      "Type": "Bid",
      "From": "Michel_M\u2026",
      "To": "",
      "Amount": "1.35\u039e ($320)",
      "Date": "Jun 13, 2020"
    },
    {
      "Type": "Bid Withdrawn",
      "From": "Michel_M\u2026",
      "To": "",
      "Amount": "1.20\u039e ($284)",
      "Date": "Jun 12, 2020"
    },
    {
      "Type": "Bid",
      "From": "Michel_M\u2026",
      "To": "",
      "Amount": "1.20\u039e ($284)",
      "Date": "Jun 12, 2020"
    },
    {
      "Type": "Offered",
      "From": "",
      "To": "",
      "Amount": "1.75\u039e ($419)",
      "Date": "Jun 03, 2020"
    },
    {
      "Type": "Claimed",
      "From": "",
      "To": "Hemba",
      "Amount": "",
      "Date": "Jun 23, 2017"
    }
  ]
}