{
  "id": "921",
  "owner": "0x8f2a8b4e36f2a058e310eee8d1c251a0a8bc0931",
  "attributes": [
    "Female",
    "Red Mohawk",
    "Regular Shades",
    "Earring",
    "Cigarette"
  ],
  "transactions": [
    {
      "Type": "Bid Withdrawn",
      "From": "0xdc5556",
      "To": "",
      "Amount": "0.20\u039e ($286)",
      "Date": "Feb 26, 2021"
    },
    {
      "Type": "Offered",
      "From": "",
      "To": "",
      "Amount": "420.69\u039e ($788,819)",
      "Date": "Feb 22, 2021"
    },
    {
      "Type": "Sold",
      "From": "Pranksy",
      "To": "0x8f2a8b",
      "Amount": "29.99\u039e ($56,233)",
      "Date": "Feb 22, 2021"
    },
    {
      "Type": "Bid",
      "From": "0xdc5556",
      "To": "",
      "Amount": "0.20\u039e ($376)",
      "Date": "Feb 22, 2021"
    },
    {
      "Type": "Offered",
      "From": "",
      "To": "",
      "Amount": "29.99\u039e ($57,015)",
      "Date": "Feb 18, 2021"
    },
    {
      "Type": "Transfer",
      "From": "0xc352b5",
      "To": "Pranksy",
      "Amount": "",
      "Date": "Feb 18, 2021"
    },
    {
      "Type": "Claimed",
      "From": "",
      "To": "0xc352b5",
      "Amount": "",
      "Date": "Jun 23, 2017"
    }
  ]
}